[
  {
    "id": 1,
    "title": "牛排",
    "foods": [
      {
        "name": "浇汁牛排",
        "img": "images/steaks/001.jpg",
        "img_lg": "images/steaks/001_lg.jpg",
        "relish": "牛排",
        "introduce": "西餐代表之一，法国风格美食。通过煎炸等工序制成，外焦黄味酥香，里鲜红味鲜嫩。",
        "price": 68,
        "number": 0,
        "active": false
      },
      {
        "name": "蒙特利尔烤牛肋骨",
        "img": "images/steaks/002.jpg",
        "img_lg": "images/steaks/002_lg.jpg",
        "relish": "牛排",
        "introduce": "西餐代表之一，法国风格美食。通过煎炸等工序制成，外焦黄味酥香，里鲜红味鲜嫩。",
        "price": 68,
        "number": 0,
        "active": false
      },
      {
        "name": "牛肋骨 黑胡椒汁",
        "img": "images/steaks/003.jpg",
        "img_lg": "images/steaks/003_lg.jpg", 
        "relish": "牛排",
        "introduce": "西餐代表之一，法国风格美食。通过煎炸等工序制成，外焦黄味酥香，里鲜红味鲜嫩。",
        "price": 68,
        "number": 0,
        "active": false
      },
      {
        "name": "史蒂芬威廉牛排",
        "img": "images/steaks/004.jpg",
        "img_lg": "images/steaks/004_lg.jpg",
        "relish": "牛排",
        "introduce": "西餐代表之一，法国风格美食。通过煎炸等工序制成，外焦黄味酥香，里鲜红味鲜嫩。",
        "price": 68,
        "number": 0,
        "active": false
      },
      {
        "name": "铁扒牛排",
        "img": "images/steaks/005.jpg",
        "img_lg": "images/steaks/005_lg.jpg",
        "relish": "牛排",
        "introduce": "西餐代表之一，法国风格美食。通过煎炸等工序制成，外焦黄味酥香，里鲜红味鲜嫩。",
        "price": 68,
        "number": 0,
        "active": false
      },
      {
        "name": "铁板黑牛排",
        "img": "images/steaks/006.jpg",
        "img_lg": "images/steaks/006_lg.jpg",
        "relish": "牛排",
        "introduce": "西餐代表之一，法国风格美食。通过煎炸等工序制成，外焦黄味酥香，里鲜红味鲜嫩。",
        "price": 68,
        "number": 0,
        "active": false
      },
      {
        "name": "铁板牛排",
        "img": "images/steaks/007.jpg",
        "img_lg": "images/steaks/007_lg.jpg",
        "relish": "牛排",
        "introduce": "西餐代表之一，法国风格美食。通过煎炸等工序制成，外焦黄味酥香，里鲜红味鲜嫩。",
        "price": 68,
        "number": 0,
        "active": false
      },
      {
        "name": "铁板牛排意面",
        "img": "images/steaks/008.jpg",
        "img_lg": "images/steaks/008_lg.jpg",
        "relish": "牛排",
        "introduce": "西餐代表之一，法国风格美食。通过煎炸等工序制成，外焦黄味酥香，里鲜红味鲜嫩。",
        "price": 68,
        "number": 0,
        "active": false
      },
      {
        "name": "铁板牛排佐蔬菜",
        "img": "images/steaks/009.jpg",
        "img_lg": "images/steaks/009_lg.jpg",
        "relish": "牛排",
        "introduce": "西餐代表之一，法国风格美食。通过煎炸等工序制成，外焦黄味酥香，里鲜红味鲜嫩。",
        "price": 68,
        "number": 0,
        "active": false
      }
    ]
  },
  {
    "id": 2,
    "title": "西餐",
    "foods": [
      {
        "name": "鲜虾意大利面",
        "img": "images/westfoods/001.jpg",
        "img_lg": "images/westfoods/001_lg.jpg",
        "relish": "西餐",
        "introduce": "西餐的准确称呼应为欧洲美食，或欧式餐饮。其菜式料理与中国菜不同，一般使用橄榄油、黄油、番茄酱、沙拉酱等调味料。",
        "price": 80,
        "number": 0,
        "active": false
      },
      {
        "name": "鱼子酱鹅肝",
        "img": "images/westfoods/002.jpg",
        "img_lg": "images/westfoods/002_lg.jpg",
        "relish": "西餐",
        "introduce": "西餐的准确称呼应为欧洲美食，或欧式餐饮。其菜式料理与中国菜不同，一般使用橄榄油、黄油、番茄酱、沙拉酱等调味料。",
        "price": 80,
        "number": 0,
        "active": false
      },
      {
        "name": "香煎鳕鱼",
        "img": "images/westfoods/003.jpg",
        "img_lg": "images/westfoods/003_lg.jpg",
        "relish": "西餐",
        "introduce": "西餐的准确称呼应为欧洲美食，或欧式餐饮。其菜式料理与中国菜不同，一般使用橄榄油、黄油、番茄酱、沙拉酱等调味料。",
        "price": 80,
        "number": 0,
        "active": false
      },
      {
        "name": "奶油焗扇贝",
        "img": "images/westfoods/004.jpg",
        "img_lg": "images/westfoods/004_lg.jpg",
        "relish": "西餐",
        "introduce": "西餐的准确称呼应为欧洲美食，或欧式餐饮。其菜式料理与中国菜不同，一般使用橄榄油、黄油、番茄酱、沙拉酱等调味料。",
        "price": 80,
        "number": 0,
        "active": false
      },
      {
        "name": "焗蜗牛",
        "img": "images/westfoods/005.jpg",
        "img_lg": "images/westfoods/005_lg.jpg",
        "relish": "西餐",
        "introduce": "西餐的准确称呼应为欧洲美食，或欧式餐饮。其菜式料理与中国菜不同，一般使用橄榄油、黄油、番茄酱、沙拉酱等调味料。",
        "price": 80,
        "number": 0,
        "active": false
      },
      {
        "name": "马铃薯浓汤",
        "img": "images/westfoods/006.jpg",
        "img_lg": "images/westfoods/006_lg.jpg",
        "relish": "西餐",
        "introduce": "西餐的准确称呼应为欧洲美食，或欧式餐饮。其菜式料理与中国菜不同，一般使用橄榄油、黄油、番茄酱、沙拉酱等调味料。",
        "price": 80,
        "number": 0,
        "active": false
      },
      {
        "name": "奶油金瓜汤",
        "img": "images/westfoods/007.jpg",
        "img_lg": "images/westfoods/007_lg.jpg",
        "relish": "西餐",
        "introduce": "西餐的准确称呼应为欧洲美食，或欧式餐饮。其菜式料理与中国菜不同，一般使用橄榄油、黄油、番茄酱、沙拉酱等调味料。",
        "price": 80,
        "number": 0,
        "active": false
      },
      {
        "name": "奶油玉米浓汤",
        "img": "images/westfoods/008.jpg",
        "img_lg": "images/westfoods/008_lg.jpg",
        "relish": "西餐",
        "introduce": "西餐的准确称呼应为欧洲美食，或欧式餐饮。其菜式料理与中国菜不同，一般使用橄榄油、黄油、番茄酱、沙拉酱等调味料。",
        "price": 80,
        "number": 0,
        "active": false
      },
      {
        "name": "香草头盘",
        "img": "images/westfoods/009.jpg",
        "img_lg": "images/westfoods/009_lg.jpg",
        "relish": "西餐",
        "introduce": "西餐的准确称呼应为欧洲美食，或欧式餐饮。其菜式料理与中国菜不同，一般使用橄榄油、黄油、番茄酱、沙拉酱等调味料。",
        "price": 80,
        "number": 0,
        "active": false
      }
    ]
  },
  {
    "id": 3,
    "title": "果汁",
    "foods": [
      {
        "name": "清爽柠檬",
        "img": "images/drinks/001.jpg",
        "img_lg": "images/drink/001_lg.jpg",
        "relish": "饮品",
        "introduce": "饮品是指能够满足人体机能正常需要，可以直接饮用，或者溶解、稀释等方式饮用的食品。",
        "price": 20,
        "number": 0,
        "active": false
      },
      {
        "name": "水果之夏",
        "img": "images/drinks/002.jpg",
        "img_lg": "images/drink/002_lg.jpg",
        "relish": "饮品",
        "introduce": "饮品是指能够满足人体机能正常需要，可以直接饮用，或者溶解、稀释等方式饮用的食品。",
        "price": 20,
        "number": 0,
        "active": false
      },
      {
        "name": "晚霞",
        "img": "images/drinks/003.jpg",
        "img_lg": "images/drink/003_lg.jpg",
        "relish": "饮品",
        "introduce": "饮品是指能够满足人体机能正常需要，可以直接饮用，或者溶解、稀释等方式饮用的食品。",
        "price": 20,
        "number": 0,
        "active": false
      },
      {
        "name": "西柚心情",
        "img": "images/drinks/004.jpg",
        "img_lg": "images/drink/004_lg.jpg",
        "relish": "饮品",
        "introduce": "饮品是指能够满足人体机能正常需要，可以直接饮用，或者溶解、稀释等方式饮用的食品。",
        "price": 20,
        "number": 0,
        "active": false
      },
      {
        "name": "夏日恋曲",
        "img": "images/drinks/005.jpg",
        "img_lg": "images/drink/005_lg.jpg",
        "relish": "饮品",
        "introduce": "饮品是指能够满足人体机能正常需要，可以直接饮用，或者溶解、稀释等方式饮用的食品。",
        "price": 20,
        "number": 0,
        "active": false
      },
      {
        "name": "相思豆",
        "img": "images/drinks/006.jpg",
        "img_lg": "images/drink/006_lg.jpg",
        "relish": "饮品",
        "introduce": "饮品是指能够满足人体机能正常需要，可以直接饮用，或者溶解、稀释等方式饮用的食品。",
        "price": 20,
        "number": 0,
        "active": false
      },
      {
        "name": "柚惑",
        "img": "images/drinks/007.jpg",
        "img_lg": "images/drink/007_lg.jpg",
        "relish": "饮品",
        "introduce": "饮品是指能够满足人体机能正常需要，可以直接饮用，或者溶解、稀释等方式饮用的食品。",
        "price": 20,
        "number": 0,
        "active": false
      },
      {
        "name": "雪菲",
        "img": "images/drinks/008.jpg",
        "img_lg": "images/drink/008_lg.jpg",
        "relish": "饮品",
        "introduce": "饮品是指能够满足人体机能正常需要，可以直接饮用，或者溶解、稀释等方式饮用的食品。",
        "price": 20,
        "number": 0,
        "active": false
      },
      {
        "name": "樱莓之恋",
        "img": "images/drinks/009.jpg",
        "img_lg": "images/drink/009_lg.jpg",
        "relish": "饮品",
        "introduce": "饮品是指能够满足人体机能正常需要，可以直接饮用，或者溶解、稀释等方式饮用的食品。",
        "price": 20,
        "number": 0,
        "active": false
      }
    ]
  },
  {
    "id": 4,
    "title": "甜点",
    "foods": [
       {
        "name": "芝士大满贯",
        "img": "images/sweetmeats/001.jpg",
        "img_lg": "images/sweetmeats/001_lg.jpg",
        "relish": "甜点",
        "introduce": "甜食是西餐中最后一道菜，食后能给人以饱足舒适的感觉。经常使用的甜食布丁类，木斯类，冻子类，水果类等。布丁一般用鸡蛋，牛奶，糖果及各种水果，干果均匀烤制而成。",
        "price": 20,
        "number": 0,
        "active": false
      },
      {
        "name": "桃花朵朵",
        "img": "images/sweetmeats/002.jpg",
        "img_lg": "images/sweetmeats/002_lg.jpg",
        "relish": "甜点",
        "introduce": "甜食是西餐中最后一道菜，食后能给人以饱足舒适的感觉。经常使用的甜食布丁类，木斯类，冻子类，水果类等。布丁一般用鸡蛋，牛奶，糖果及各种水果，干果均匀烤制而成。",
        "price": 20,
        "number": 0,
        "active": false
      },
      {
        "name": "浓情慕斯",
        "img": "images/sweetmeats/003.jpg",
        "img_lg": "images/sweetmeats/003_lg.jpg",
        "relish": "甜点",
        "introduce": "甜食是西餐中最后一道菜，食后能给人以饱足舒适的感觉。经常使用的甜食布丁类，木斯类，冻子类，水果类等。布丁一般用鸡蛋，牛奶，糖果及各种水果，干果均匀烤制而成。",
        "price": 20,
        "number": 0,
        "active": false
      },
      {
        "name": "蓝莓慕斯",
        "img": "images/sweetmeats/004.jpg",
        "img_lg": "images/sweetmeats/004_lg.jpg",
        "relish": "甜点",
        "introduce": "甜食是西餐中最后一道菜，食后能给人以饱足舒适的感觉。经常使用的甜食布丁类，木斯类，冻子类，水果类等。布丁一般用鸡蛋，牛奶，糖果及各种水果，干果均匀烤制而成。",
        "price": 20,
        "number": 0,
        "active": false
      },
      {
        "name": "健康杂粮",
        "img": "images/sweetmeats/005.jpg",
        "img_lg": "images/sweetmeats/005_lg.jpg",
        "relish": "甜点",
        "introduce": "甜食是西餐中最后一道菜，食后能给人以饱足舒适的感觉。经常使用的甜食布丁类，木斯类，冻子类，水果类等。布丁一般用鸡蛋，牛奶，糖果及各种水果，干果均匀烤制而成。",
        "price": 20,
        "number": 0,
        "active": false
      },
      {
        "name": "丹麦风情",
        "img": "images/sweetmeats/006.jpg",
        "img_lg": "images/sweetmeats/006_lg.jpg",
        "relish": "甜点",
        "introduce": "甜食是西餐中最后一道菜，食后能给人以饱足舒适的感觉。经常使用的甜食布丁类，木斯类，冻子类，水果类等。布丁一般用鸡蛋，牛奶，糖果及各种水果，干果均匀烤制而成。",
        "price": 20,
        "number": 0,
        "active": false
      },
      {
        "name": "留恋",
        "img": "images/sweetmeats/007.jpg",
        "img_lg": "images/sweetmeats/007_lg.jpg",
        "relish": "甜点",
        "introduce": "甜食是西餐中最后一道菜，食后能给人以饱足舒适的感觉。经常使用的甜食布丁类，木斯类，冻子类，水果类等。布丁一般用鸡蛋，牛奶，糖果及各种水果，干果均匀烤制而成。",
        "price": 20,
        "number": 0,
        "active": false
      },
      {
        "name": "繁星点点",
        "img": "images/sweetmeats/008.jpg",
        "img_lg": "images/sweetmeats/008_lg.jpg",
        "relish": "甜点",
        "introduce": "甜食是西餐中最后一道菜，食后能给人以饱足舒适的感觉。经常使用的甜食布丁类，木斯类，冻子类，水果类等。布丁一般用鸡蛋，牛奶，糖果及各种水果，干果均匀烤制而成。",
        "price": 20,
        "number": 0,
        "active": false
      },
      {
        "name": "思绪万千",
        "img": "images/sweetmeats/009.jpg",
        "img_lg": "images/sweetmeats/009_lg.jpg",
        "relish": "甜点",
        "introduce": "甜食是西餐中最后一道菜，食后能给人以饱足舒适的感觉。经常使用的甜食布丁类，木斯类，冻子类，水果类等。布丁一般用鸡蛋，牛奶，糖果及各种水果，干果均匀烤制而成。",
        "price": 20,
        "number": 0,
        "active": false
      }
    ]
  },
  {
    "id": 5,
    "title": "咖啡",
    "foods": [
      {
        "name": "Cappuccino1",
        "img": "images/coffees/001.jpg",
        "img_lg": "images/coffees/001_lg.jpg",
        "relish": "咖啡",
        "introduce": "在世界各地，人们越来越爱喝咖啡。随之而来的“咖啡文化”充满生活的每个时刻。无论在家里、还是在办公室、或是各种社交场合，人们都在品着咖啡、它逐渐与时尚、现代生活联系在一起。",
        "price": 40,
        "number": 0,
        "active": false
      },
      {
        "name": "Cappuccino2",
        "img": "images/coffees/002.jpg",
        "img_lg": "images/coffees/002_lg.jpg",
        "relish": "咖啡",
        "introduce": "在世界各地，人们越来越爱喝咖啡。随之而来的“咖啡文化”充满生活的每个时刻。无论在家里、还是在办公室、或是各种社交场合，人们都在品着咖啡、它逐渐与时尚、现代生活联系在一起。",
        "price": 40,
        "number": 0,
        "active": false
      },
      {
        "name": "Americano1",
        "img": "images/coffees/003.jpg",
        "img_lg": "images/coffees/003_lg.jpg",
        "relish": "咖啡",
        "introduce": "在世界各地，人们越来越爱喝咖啡。随之而来的“咖啡文化”充满生活的每个时刻。无论在家里、还是在办公室、或是各种社交场合，人们都在品着咖啡、它逐渐与时尚、现代生活联系在一起。",
        "price": 40,
        "number": 0,
        "active": false
      },
      {
        "name": "Americano2",
        "img": "images/coffees/004.jpg",
        "img_lg": "images/coffees/004_lg.jpg",
        "relish": "咖啡",
        "introduce": "在世界各地，人们越来越爱喝咖啡。随之而来的“咖啡文化”充满生活的每个时刻。无论在家里、还是在办公室、或是各种社交场合，人们都在品着咖啡、它逐渐与时尚、现代生活联系在一起。",
        "price": 40,
        "number": 0,
        "active": false
      },
      {
        "name": "Cafe Mocha1",
        "img": "images/coffees/005.jpg",
        "img_lg": "images/coffees/005_lg.jpg",
        "relish": "咖啡",
        "introduce": "在世界各地，人们越来越爱喝咖啡。随之而来的“咖啡文化”充满生活的每个时刻。无论在家里、还是在办公室、或是各种社交场合，人们都在品着咖啡、它逐渐与时尚、现代生活联系在一起。",
        "price": 40,
        "number": 0,
        "active": false
      },
      {
        "name": "Cafe Mocha2",
        "img": "images/coffees/006.jpg",
        "img_lg": "images/coffees/006_lg.jpg",
        "relish": "咖啡",
        "introduce": "在世界各地，人们越来越爱喝咖啡。随之而来的“咖啡文化”充满生活的每个时刻。无论在家里、还是在办公室、或是各种社交场合，人们都在品着咖啡、它逐渐与时尚、现代生活联系在一起。",
        "price": 40,
        "number": 0,
        "active": false
      },
      {
        "name": "Cafe Mocha3",
        "img": "images/coffees/007.jpg",
        "img_lg": "images/coffees/007_lg.jpg",
        "relish": "咖啡",
        "introduce": "在世界各地，人们越来越爱喝咖啡。随之而来的“咖啡文化”充满生活的每个时刻。无论在家里、还是在办公室、或是各种社交场合，人们都在品着咖啡、它逐渐与时尚、现代生活联系在一起。",
        "price": 40,
        "number": 0,
        "active": false
      },
      {
        "name": "Espresso Con Panna1",
        "img": "images/coffees/008.jpg",
        "img_lg": "images/coffees/008_lg.jpg",
        "relish": "咖啡",
        "introduce": "在世界各地，人们越来越爱喝咖啡。随之而来的“咖啡文化”充满生活的每个时刻。无论在家里、还是在办公室、或是各种社交场合，人们都在品着咖啡、它逐渐与时尚、现代生活联系在一起。",
        "price": 40,
        "number": 0,
        "active": false
      },
      {
        "name": "Espresso Con Panna2",
        "img": "images/coffees/009.jpg",
        "img_lg": "images/coffees/009_lg.jpg",
        "relish": "咖啡",
        "introduce": "在世界各地，人们越来越爱喝咖啡。随之而来的“咖啡文化”充满生活的每个时刻。无论在家里、还是在办公室、或是各种社交场合，人们都在品着咖啡、它逐渐与时尚、现代生活联系在一起。",
        "price": 40,
        "number": 0,
        "active": false
      }
    ]
  }
]